dpgtheminator/__init__.py
dpgtheminator/controller.py
dpgtheminator/exceptions.py
dpgtheminator/models.py
dpgtheminator/py.typed
dpgtheminator/util.py
dpgtheminator/default_palettes/catppuccin_frappe.json
dpgtheminator/default_palettes/catppuccin_latte.json
dpgtheminator/default_palettes/catppuccin_macchiato.json
dpgtheminator/default_palettes/catppuccin_mocha.json
dpgtheminator/default_themes/catppuccin_frappe.json
dpgtheminator/default_themes/catppuccin_latte.json
dpgtheminator/default_themes/catppuccin_macchiato.json
dpgtheminator/default_themes/catppuccin_mocha.json
dpgtheminator/default_themes/dark.json
dpgtheminator/default_themes/light.json
dpgtheminator/default_themes/light2.json
dpgtheminator/demo/__main__.py
dpgtheminator/gui/theminator.py
dpgtheminator-0.1.0.dist-info/METADATA
dpgtheminator-0.1.0.dist-info/WHEEL
dpgtheminator-0.1.0.dist-info/RECORD
