Metadata-Version: 2.4
Name: dpgtheminator
Version: 0.1.0
Summary: Add your description here
Author-email: Zachary Parmley <zachary.parmley@gmail.com>
Requires-Python: >=3.13
Requires-Dist: dearpygui>=2.1.0
Requires-Dist: dpgcontainers>=0.1.8
Requires-Dist: msgspec>=0.19.0
